mosaic_utils/__init__.py
mosaic_utils/ai/__init__.py
mosaic_utils/ai/decorators.py
mosaic_utils/ai/encoding_utils.py
mosaic_utils/ai/file_utils.py
mosaic_utils/ai/audit_log/__init__.py
mosaic_utils/ai/audit_log/constants.py
mosaic_utils/ai/audit_log/utils.py
mosaic_utils/ai/build_time_metrics/__init__.py
mosaic_utils/ai/build_time_metrics/constants.py
mosaic_utils/ai/build_time_metrics/metrics.py
mosaic_utils/ai/build_time_metrics/utils.py
mosaic_utils/ai/data_files/__init__.py
mosaic_utils/ai/data_files/constants.py
mosaic_utils/ai/data_files/utils.py
mosaic_utils/ai/flavours/__init__.py
mosaic_utils/ai/flavours/keras.py
mosaic_utils/ai/flavours/pmml.py
mosaic_utils/ai/flavours/pyspark.py
mosaic_utils/ai/flavours/pytorch.py
mosaic_utils/ai/flavours/r.py
mosaic_utils/ai/flavours/sklearn.py
mosaic_utils/ai/flavours/spacy.py
mosaic_utils/ai/flavours/tensorflow.py
mosaic_utils/ai/flavours/utils.py
mosaic_utils/ai/flavours/xgboost.py
mosaic_utils/ai/git_repo/__init__.py
mosaic_utils/ai/git_repo/constants.py
mosaic_utils/ai/git_repo/utils.py
mosaic_utils/ai/headers/__init__.py
mosaic_utils/ai/headers/constants.py
mosaic_utils/ai/headers/utils.py
mosaic_utils/ai/input_params/__init__.py
mosaic_utils/ai/input_params/contants.py
mosaic_utils/ai/input_params/utils.py
mosaic_utils/ai/k8/__init__.py
mosaic_utils/ai/k8/constants.py
mosaic_utils/ai/k8/pod_metrics_summary.py
mosaic_utils/ai/k8/utils.py
mosaic_utils/ai/kerberos/__init__.py
mosaic_utils/ai/kerberos/utils.py
mosaic_utils/ai/logger/__init__.py
mosaic_utils/ai/logger/utils.py
mosaic_utils/ai/mosaicautoml/__init__.py
mosaic_utils/ai/mosaicautoml/combine_dfs.py
mosaic_utils/ai/mosaicautoml/feature_set_selector.py
mosaic_utils/ai/mosaicautoml/feature_transformers.py
mosaic_utils/ai/mosaicautoml/helmert_encoder.py
mosaic_utils/ai/mosaicautoml/one_hot_encoder.py
mosaic_utils/ai/mosaicautoml/preprocessing.py
mosaic_utils/ai/mosaicautoml/stacking_estimator.py
mosaic_utils/ai/mosaicautoml/target_encoder.py
mosaic_utils-1.0.2.dist-info/METADATA
mosaic_utils-1.0.2.dist-info/WHEEL
mosaic_utils-1.0.2.dist-info/top_level.txt
mosaic_utils-1.0.2.dist-info/RECORD
