Metadata-Version: 2.1
Name: mosaic-utils
Version: 1.0.2
Summary: Utils library for Mosaic
Home-page: https://git.lti-aiq.in/mosaic-ai-logistics/mosaic-common-utils
Author: Rushikesh Raut
Author-email: rushikesh.raut@lntinfotech.com
License: UNKNOWN
Platform: UNKNOWN
Classifier: Programming Language :: Python :: 3.8
Requires-Dist: scikit-learn (==0.21.3) ; python_version <= "3.7"
Requires-Dist: scikit-learn (==1.2.1) ; python_version >= "3.8"
Provides-Extra: common
Requires-Dist: cloudpickle (==1.2.2) ; extra == 'common'
Requires-Dist: minio (==4.0.18) ; extra == 'common'
Requires-Dist: GitPython (==3.0.4) ; extra == 'common'
Requires-Dist: gitdb2 (==2.0.6) ; extra == 'common'
Requires-Dist: ipython (>=7.11.1) ; extra == 'common'
Provides-Extra: complete
Requires-Dist: GitPython (==3.0.4) ; extra == 'complete'
Requires-Dist: PyYAML (==5.4.1) ; extra == 'complete'
Requires-Dist: bs4 (==0.0.1) ; extra == 'complete'
Requires-Dist: category-encoders (==2.2.2) ; extra == 'complete'
Requires-Dist: cloudpickle (==1.2.2) ; extra == 'complete'
Requires-Dist: gitdb2 (==2.0.6) ; extra == 'complete'
Requires-Dist: ipython (>=7.11.1) ; extra == 'complete'
Requires-Dist: keras (==2.2.4) ; extra == 'complete'
Requires-Dist: kubernetes (==9.0.0) ; extra == 'complete'
Requires-Dist: minio (==4.0.18) ; extra == 'complete'
Requires-Dist: nltk (==3.5) ; extra == 'complete'
Requires-Dist: numpy (>=1.16.5) ; extra == 'complete'
Requires-Dist: pandas (==1.0.4) ; extra == 'complete'
Requires-Dist: pyspark (==2.4.6) ; extra == 'complete'
Requires-Dist: requests (==2.22.0) ; extra == 'complete'
Requires-Dist: scikit-learn (==0.21.3) ; extra == 'complete'
Requires-Dist: sklearn (==0.0) ; extra == 'complete'
Requires-Dist: spacy (==2.2.2) ; extra == 'complete'
Requires-Dist: tensorflow-probability (==0.11.1) ; extra == 'complete'
Requires-Dist: tensorflow (==2.4.1) ; extra == 'complete'
Requires-Dist: torch (==1.2.0) ; extra == 'complete'
Requires-Dist: torch (==1.8.0) ; extra == 'complete'
Requires-Dist: torchvision (==0.4.0) ; extra == 'complete'
Requires-Dist: torchvision (==0.8.0) ; extra == 'complete'
Provides-Extra: complete_lite
Requires-Dist: GitPython (==3.0.4) ; extra == 'complete_lite'
Requires-Dist: PyYAML (==5.4.1) ; extra == 'complete_lite'
Requires-Dist: bs4 (==0.0.1) ; extra == 'complete_lite'
Requires-Dist: category-encoders (==2.2.2) ; extra == 'complete_lite'
Requires-Dist: cloudpickle (==1.2.2) ; extra == 'complete_lite'
Requires-Dist: gitdb2 (==2.0.6) ; extra == 'complete_lite'
Requires-Dist: ipython (>=7.11.1) ; extra == 'complete_lite'
Requires-Dist: kubernetes (==9.0.0) ; extra == 'complete_lite'
Requires-Dist: minio (==4.0.18) ; extra == 'complete_lite'
Requires-Dist: nltk (==3.5) ; extra == 'complete_lite'
Requires-Dist: numpy (>=1.16.5) ; extra == 'complete_lite'
Requires-Dist: pandas (==1.0.4) ; extra == 'complete_lite'
Requires-Dist: requests (==2.22.0) ; extra == 'complete_lite'
Provides-Extra: flavours
Requires-Dist: keras (==2.2.4) ; extra == 'flavours'
Requires-Dist: pyspark (==2.4.6) ; extra == 'flavours'
Requires-Dist: sklearn (==0.0) ; extra == 'flavours'
Requires-Dist: tensorflow (==2.4.1) ; extra == 'flavours'
Requires-Dist: tensorflow-probability (==0.11.1) ; extra == 'flavours'
Requires-Dist: torch (==1.2.0) ; extra == 'flavours'
Requires-Dist: torchvision (==0.4.0) ; extra == 'flavours'
Requires-Dist: spacy (==2.2.2) ; extra == 'flavours'
Requires-Dist: scikit-learn (==0.21.3) ; extra == 'flavours'
Provides-Extra: flavours_lite
Provides-Extra: k8
Requires-Dist: kubernetes (==9.0.0) ; extra == 'k8'
Requires-Dist: numpy (>=1.16.5) ; extra == 'k8'
Requires-Dist: pandas (==1.0.4) ; extra == 'k8'
Requires-Dist: sklearn (==0.0) ; extra == 'k8'
Requires-Dist: scikit-learn (==0.21.3) ; extra == 'k8'
Provides-Extra: metrics
Requires-Dist: numpy (>=1.16.5) ; extra == 'metrics'
Requires-Dist: requests (==2.22.0) ; extra == 'metrics'
Requires-Dist: pandas (==1.0.4) ; extra == 'metrics'
Requires-Dist: sklearn (==0.0) ; extra == 'metrics'
Requires-Dist: PyYAML (==5.4.1) ; extra == 'metrics'
Requires-Dist: scikit-learn (==0.21.3) ; extra == 'metrics'
Requires-Dist: ipython (>=7.11.1) ; extra == 'metrics'
Provides-Extra: metrics_lite
Requires-Dist: PyYAML (==5.4.1) ; extra == 'metrics_lite'
Requires-Dist: ipython (>=7.11.1) ; extra == 'metrics_lite'
Requires-Dist: numpy (>=1.16.5) ; extra == 'metrics_lite'
Requires-Dist: pandas (==1.0.4) ; extra == 'metrics_lite'
Requires-Dist: requests (==2.22.0) ; extra == 'metrics_lite'
Provides-Extra: mosaicautoml
Requires-Dist: numpy (>=1.16.5) ; extra == 'mosaicautoml'
Requires-Dist: pandas (==1.0.4) ; extra == 'mosaicautoml'
Requires-Dist: sklearn (==0.0) ; extra == 'mosaicautoml'
Requires-Dist: category-encoders (==2.2.2) ; extra == 'mosaicautoml'
Requires-Dist: nltk (==3.5) ; extra == 'mosaicautoml'
Requires-Dist: bs4 (==0.0.1) ; extra == 'mosaicautoml'
Provides-Extra: mosaicautoml_lite
Requires-Dist: bs4 (==0.0.1) ; extra == 'mosaicautoml_lite'
Requires-Dist: category-encoders (==2.2.2) ; extra == 'mosaicautoml_lite'
Requires-Dist: nltk (==3.5) ; extra == 'mosaicautoml_lite'
Requires-Dist: numpy (>=1.16.5) ; extra == 'mosaicautoml_lite'
Requires-Dist: pandas (==1.0.4) ; extra == 'mosaicautoml_lite'
Provides-Extra: nb-template-serving
Requires-Dist: cloudpickle (==1.2.2) ; extra == 'nb-template-serving'
Requires-Dist: PyYAML (==5.4.1) ; extra == 'nb-template-serving'
Provides-Extra: nb_api
Requires-Dist: GitPython (==3.0.4) ; extra == 'nb_api'
Requires-Dist: gitdb2 (==2.0.6) ; extra == 'nb_api'
Requires-Dist: kubernetes (==9.0.0) ; extra == 'nb_api'
Requires-Dist: numpy (>=1.16.5) ; extra == 'nb_api'
Requires-Dist: pandas (==1.0.4) ; extra == 'nb_api'
Requires-Dist: scikit-learn (==0.21.3) ; extra == 'nb_api'
Requires-Dist: sklearn (==0.0) ; extra == 'nb_api'
Provides-Extra: pmml
Requires-Dist: GitPython (==3.0.4) ; extra == 'pmml'
Requires-Dist: PyYAML (==5.4.1) ; extra == 'pmml'
Requires-Dist: bs4 (==0.0.1) ; extra == 'pmml'
Requires-Dist: category-encoders (==2.2.2) ; extra == 'pmml'
Requires-Dist: cloudpickle (==1.2.2) ; extra == 'pmml'
Requires-Dist: gitdb2 (==2.0.6) ; extra == 'pmml'
Requires-Dist: ipython (>=7.11.1) ; extra == 'pmml'
Requires-Dist: keras (==2.2.4) ; extra == 'pmml'
Requires-Dist: kubernetes (==9.0.0) ; extra == 'pmml'
Requires-Dist: minio (==4.0.18) ; extra == 'pmml'
Requires-Dist: nltk (==3.5) ; extra == 'pmml'
Requires-Dist: numpy (>=1.16.5) ; extra == 'pmml'
Requires-Dist: pandas (==1.0.4) ; extra == 'pmml'
Requires-Dist: requests (==2.22.0) ; extra == 'pmml'
Requires-Dist: scikit-learn (==0.21.3) ; extra == 'pmml'
Requires-Dist: sklearn (==0.0) ; extra == 'pmml'
Requires-Dist: spacy (==2.2.2) ; extra == 'pmml'
Requires-Dist: tensorflow-probability (==0.11.1) ; extra == 'pmml'
Requires-Dist: tensorflow (==2.4.1) ; extra == 'pmml'
Requires-Dist: torch (==1.2.0) ; extra == 'pmml'
Requires-Dist: torch (==1.8.0) ; extra == 'pmml'
Requires-Dist: torchvision (==0.4.0) ; extra == 'pmml'
Requires-Dist: torchvision (==0.8.0) ; extra == 'pmml'
Requires-Dist: pypmml (==0.9.5) ; extra == 'pmml'
Provides-Extra: pmml_lite
Requires-Dist: GitPython (==3.0.4) ; extra == 'pmml_lite'
Requires-Dist: PyYAML (==5.4.1) ; extra == 'pmml_lite'
Requires-Dist: bs4 (==0.0.1) ; extra == 'pmml_lite'
Requires-Dist: category-encoders (==2.2.2) ; extra == 'pmml_lite'
Requires-Dist: cloudpickle (==1.2.2) ; extra == 'pmml_lite'
Requires-Dist: gitdb2 (==2.0.6) ; extra == 'pmml_lite'
Requires-Dist: ipython (>=7.11.1) ; extra == 'pmml_lite'
Requires-Dist: kubernetes (==9.0.0) ; extra == 'pmml_lite'
Requires-Dist: minio (==4.0.18) ; extra == 'pmml_lite'
Requires-Dist: nltk (==3.5) ; extra == 'pmml_lite'
Requires-Dist: numpy (>=1.16.5) ; extra == 'pmml_lite'
Requires-Dist: pandas (==1.0.4) ; extra == 'pmml_lite'
Requires-Dist: pypmml (==0.9.5) ; extra == 'pmml_lite'
Requires-Dist: requests (==2.22.0) ; extra == 'pmml_lite'
Provides-Extra: r-jupyter
Requires-Dist: torch (==1.8.0) ; extra == 'r-jupyter'
Requires-Dist: torchvision (==0.8.0) ; extra == 'r-jupyter'
Requires-Dist: PyYAML (==5.4.1) ; extra == 'r-jupyter'
Requires-Dist: scikit-learn (==0.21.3) ; extra == 'r-jupyter'
Provides-Extra: r-jupyter_lite
Requires-Dist: PyYAML (==5.4.1) ; extra == 'r-jupyter_lite'
Provides-Extra: rstudio
Requires-Dist: GitPython (==3.0.4) ; extra == 'rstudio'
Requires-Dist: PyYAML (==5.4.1) ; extra == 'rstudio'
Requires-Dist: bs4 (==0.0.1) ; extra == 'rstudio'
Requires-Dist: category-encoders (==2.2.2) ; extra == 'rstudio'
Requires-Dist: cloudpickle (==1.2.2) ; extra == 'rstudio'
Requires-Dist: gitdb2 (==2.0.6) ; extra == 'rstudio'
Requires-Dist: ipython (>=7.11.1) ; extra == 'rstudio'
Requires-Dist: keras (==2.2.4) ; extra == 'rstudio'
Requires-Dist: kubernetes (==9.0.0) ; extra == 'rstudio'
Requires-Dist: minio (==4.0.18) ; extra == 'rstudio'
Requires-Dist: nltk (==3.5) ; extra == 'rstudio'
Requires-Dist: numpy (>=1.16.5) ; extra == 'rstudio'
Requires-Dist: pyspark (==2.4.6) ; extra == 'rstudio'
Requires-Dist: requests (==2.22.0) ; extra == 'rstudio'
Requires-Dist: scikit-learn (==0.21.3) ; extra == 'rstudio'
Requires-Dist: sklearn (==0.0) ; extra == 'rstudio'
Requires-Dist: spacy (==2.2.2) ; extra == 'rstudio'
Requires-Dist: torch (==1.8.0) ; extra == 'rstudio'
Requires-Dist: torchvision (==0.8.0) ; extra == 'rstudio'
Provides-Extra: rstudio_lite
Requires-Dist: GitPython (==3.0.4) ; extra == 'rstudio_lite'
Requires-Dist: PyYAML (==5.4.1) ; extra == 'rstudio_lite'
Requires-Dist: bs4 (==0.0.1) ; extra == 'rstudio_lite'
Requires-Dist: category-encoders (==2.2.2) ; extra == 'rstudio_lite'
Requires-Dist: cloudpickle (==1.2.2) ; extra == 'rstudio_lite'
Requires-Dist: gitdb2 (==2.0.6) ; extra == 'rstudio_lite'
Requires-Dist: ipython (>=7.11.1) ; extra == 'rstudio_lite'
Requires-Dist: kubernetes (==9.0.0) ; extra == 'rstudio_lite'
Requires-Dist: minio (==4.0.18) ; extra == 'rstudio_lite'
Requires-Dist: nltk (==3.5) ; extra == 'rstudio_lite'
Requires-Dist: numpy (>=1.16.5) ; extra == 'rstudio_lite'
Requires-Dist: requests (==2.22.0) ; extra == 'rstudio_lite'
